{"sections":{"9de27e1e-9c24-4334-982b-86e9980a73bd":{"type":"scrolling-text","blocks":{"template--17027745972539__9de27e1e-9c24-4334-982b-86e9980a73bd-1669829603416565ad-0":{"type":"text","settings":{"text":"{{ collection.title }}","link":"","outline_text":false}},"template--17027745972539__9de27e1e-9c24-4334-982b-86e9980a73bd-1669829603416565ad-1":{"type":"text","settings":{"text":"{{ collection.title }}","link":"","outline_text":false}},"template--17027745972539__9de27e1e-9c24-4334-982b-86e9980a73bd-1669829603416565ad-2":{"type":"text","settings":{"text":"{{ collection.title }}","link":"","outline_text":false}}},"block_order":["template--17027745972539__9de27e1e-9c24-4334-982b-86e9980a73bd-1669829603416565ad-0","template--17027745972539__9de27e1e-9c24-4334-982b-86e9980a73bd-1669829603416565ad-1","template--17027745972539__9de27e1e-9c24-4334-982b-86e9980a73bd-1669829603416565ad-2"],"settings":{"height":"height-auto","full_width":true,"direction":"left","speed":"20s","font_family":"body","text_size":70,"text_uppercase":true,"image_size":"medium","color_bg":"#fffce2","color_text":"#1e4e1c","overlay_color":"#000000","overlay_opacity":0,"disable_top_spacing":true,"disable_bottom_spacing":true}},"13c1fa9b-e669-46a9-8040-f6f0e85ee079":{"type":"spacer","settings":{"spacer_mobile":25,"spacer_desktop":30,"border_separator":false,"border_separator_full":false}},"main-collection-banner":{"type":"main-collection-banner","disabled":true,"settings":{"show_collection_image":true,"show_collection_description":true,"show_subcollections":true,"make_heading_uppercase":true,"text_alignment":"center","overlay_color":"#000000","overlay_opacity":40}},"product-grid":{"type":"main-collection-product-grid","settings":{"full_width":true,"products_per_page":48,"columns_desktop":3,"pagination_type":"loadmore","enable_filtering":false,"enable_sorting":false,"show_counts":false,"filter_color_swatches":false,"facets_desktop":"sidebar","sidebar_size":"medium"}},"multicolumn_products_WwVyDJ":{"type":"multicolumn-products","name":"Multicolumn Products","settings":{"heading":"Multicolumn","heading_left":false,"description":"<p>Add a short description for this section<\/p>","full_width":true,"display_type":"grid","image_ratio":"adapt","products_list":"collection","collection_for_products_list":"","products_for_products_list":[],"columns_desktop":4,"show_product_image":"metafield","show_product_title":"hide","show_product_description":"metafield","image_full_width":false,"text_alignment":"left","heading_size":"h5","mobile_swipe":true,"show_progress_bar":true,"disable_top_spacing":false,"disable_bottom_spacing":false}}},"order":["9de27e1e-9c24-4334-982b-86e9980a73bd","13c1fa9b-e669-46a9-8040-f6f0e85ee079","main-collection-banner","product-grid","multicolumn_products_WwVyDJ"]}